README.md
setup.cfg
setup.py
msa_to_gfa/Graph.py
msa_to_gfa/Node.py
msa_to_gfa/__init__.py
msa_to_gfa/check_similar_sequences.py
msa_to_gfa/compact.py
msa_to_gfa/fasta_reader.py
msa_to_gfa/graph_io.py
msa_to_gfa/main.py
msa_to_gfa/msa_to_gfa.py
msa_to_gfa/topological_sorting.py
msa_to_gfa.egg-info/PKG-INFO
msa_to_gfa.egg-info/SOURCES.txt
msa_to_gfa.egg-info/dependency_links.txt
msa_to_gfa.egg-info/entry_points.txt
msa_to_gfa.egg-info/top_level.txt