Metadata-Version: 2.1
Name: msa-to-gfa
Version: 1.0.1
Summary: convertes an MSA in FASTA to a GFA1 file with imbedded paths
Home-page: https://github.com/fawaz-dabbaghieh/msa_to_gfa
Author: Fawaz Dabbaghie
Author-email: fawaz@hhu.de
License: LICENSE.TXT
Platform: UNKNOWN
